genai_forge/__init__.py
genai_forge/chunker_implementations/__init__.py
genai_forge/chunkers/__init__.py
genai_forge/chunkers/base.py
genai_forge/chunkers/character_chunker.py
genai_forge/chunkers/registry.py
genai_forge/chunkers/semantic_chunker.py
genai_forge/chunkers/sentence_chunker.py
genai_forge/chunkers/token_chunker.py
genai_forge/embedding_providers/__init__.py
genai_forge/embedding_providers/cohere_emb.py
genai_forge/embedding_providers/google_emb.py
genai_forge/embedding_providers/mistral_emb.py
genai_forge/embedding_providers/openai_emb.py
genai_forge/embeddings/__init__.py
genai_forge/embeddings/base.py
genai_forge/embeddings/registry.py
genai_forge/llm/__init__.py
genai_forge/llm/base.py
genai_forge/llm/llm_call.py
genai_forge/llm/registry.py
genai_forge/parsing/__init__.py
genai_forge/parsing/output_parser.py
genai_forge/providers/__init__.py
genai_forge/providers/anthropic.py
genai_forge/providers/cohere.py
genai_forge/providers/google.py
genai_forge/providers/mistral.py
genai_forge/providers/openai.py
genai_forge-0.2.5.dist-info/METADATA
genai_forge-0.2.5.dist-info/WHEEL
genai_forge-0.2.5.dist-info/licenses/LICENSE
genai_forge-0.2.5.dist-info/RECORD
