Metadata-Version: 2.4
Name: genai-forge
Version: 0.2.5
Summary: Generative AI tools from ToolForge-AI organization
Project-URL: Homepage, https://github.com/ToolForge-AI/genai-forge
Project-URL: Repository, https://github.com/ToolForge-AI/genai-forge
Project-URL: Issues, https://github.com/your-org/ToolForge-AI/issues
Author-email: Daniel Aguilera <daniel.aguilera@toolforge-ai.com>
License-File: LICENSE
Requires-Python: <4.0,>=3.10
Requires-Dist: openai>=2.7.1
Requires-Dist: prompting-forge>=0.2.1
Requires-Dist: pydantic>=2.5.0
Requires-Dist: python-dotenv>=1.0.0
Requires-Dist: tiktoken>=0.12.0
Provides-Extra: all
Requires-Dist: anthropic>=0.40.0; extra == 'all'
Requires-Dist: cohere>=5.11.0; extra == 'all'
Requires-Dist: google-generativeai>=0.8.0; extra == 'all'
Requires-Dist: mistralai>=1.0.0; extra == 'all'
Requires-Dist: tiktoken>=0.5.0; extra == 'all'
Provides-Extra: anthropic
Requires-Dist: anthropic>=0.40.0; extra == 'anthropic'
Provides-Extra: chunkers
Requires-Dist: tiktoken>=0.5.0; extra == 'chunkers'
Provides-Extra: cohere
Requires-Dist: cohere>=5.11.0; extra == 'cohere'
Provides-Extra: google
Requires-Dist: google-generativeai>=0.8.0; extra == 'google'
Provides-Extra: mistral
Requires-Dist: mistralai>=1.0.0; extra == 'mistral'
